scperturb/__init__.py
scperturb/edistance.py
scperturb/etest.py
scperturb/utils.py
scperturb-0.1.0.dist-info/LICENSE
scperturb-0.1.0.dist-info/METADATA
scperturb-0.1.0.dist-info/WHEEL
scperturb-0.1.0.dist-info/top_level.txt
scperturb-0.1.0.dist-info/RECORD
