Metadata-Version: 2.1
Name: scperturb
Version: 0.1.0
Summary: Python package with E-distance tools for single-cell perturbation data analysis.
Home-page: https://github.com/sanderlab/scPerturb
Author: Stefan Peidli
Author-email: stefanpeidli@gmail.com
Project-URL: Bug Tracker, https://github.com/sanderlab/scPerturb/issues
Classifier: Programming Language :: Python :: 3
Classifier: License :: OSI Approved :: MIT License
Classifier: Operating System :: OS Independent
Classifier: Development Status :: 3 - Alpha
Classifier: Intended Audience :: Science/Research
Classifier: Natural Language :: English
Classifier: Topic :: Scientific/Engineering :: Bio-Informatics
Requires-Python: >=3.6
License-File: LICENSE
Requires-Dist: pandas >=1.1
Requires-Dist: scanpy >=1.7
Requires-Dist: tqdm >=4.62
Requires-Dist: numpy
Requires-Dist: scipy
Requires-Dist: scikit-learn
Requires-Dist: statsmodels
